vector2dggs/__init__.py
vector2dggs/cli.py
vector2dggs/common.py
vector2dggs/constants.py
vector2dggs/geohash.py
vector2dggs/h3.py
vector2dggs/katana.py
vector2dggs/rHP.py
vector2dggs/s2.py
vector2dggs-0.11.0.dist-info/COPYING
vector2dggs-0.11.0.dist-info/COPYING.LESSER
vector2dggs-0.11.0.dist-info/METADATA
vector2dggs-0.11.0.dist-info/WHEEL
vector2dggs-0.11.0.dist-info/entry_points.txt
vector2dggs-0.11.0.dist-info/RECORD
