Metadata-Version: 2.1
Name: vector2dggs
Version: 0.11.0
Summary: CLI DGGS indexer for vector geospatial data
Home-page: https://github.com/manaakiwhenua/vector2dggs
License: LGPL-3.0-or-later
Keywords: dggs,vector,h3,rHEALPix,cli
Author: James Ardo
Author-email: ardoj@landcareresearch.co.nz
Maintainer: Richard Law
Maintainer-email: lawr@landcareresearch.co.nz
Requires-Python: >=3.11,<4.0
Classifier: License :: OSI Approved :: GNU Lesser General Public License v3 or later (LGPLv3+)
Classifier: Programming Language :: Python :: 3
Classifier: Programming Language :: Python :: 3.11
Classifier: Topic :: Scientific/Engineering
Classifier: Topic :: Scientific/Engineering :: GIS
Classifier: Topic :: Scientific/Engineering :: Information Analysis
Requires-Dist: click (>=8.1.7,<9.0.0)
Requires-Dist: click-log (>=0.4.0,<0.5.0)
Requires-Dist: dask (>=2025.1,<2026.0)
Requires-Dist: dask-geopandas (>=0.5,<0.6)
Requires-Dist: gdal (>=3.8,<4.0)
Requires-Dist: geopandas (>=1.0.1,<2.0.0)
Requires-Dist: h3pandas (>=0.3,<0.4)
Requires-Dist: numpy (>=2,<3)
Requires-Dist: pillow (>=11.2.1,<12.0.0)
Requires-Dist: psycopg2 (>=2.9.9,<3.0.0)
Requires-Dist: pyarrow (>=20.0,<21.0)
Requires-Dist: pyproj (>=3.7,<4.0)
Requires-Dist: python-geohash (>=0.8.5,<0.9.0)
Requires-Dist: rhealpixdggs (>=0.5.12,<0.6.0)
Requires-Dist: rhppandas (>=0.2.0,<0.3.0)
Requires-Dist: rusty-polygon-geohasher (>=0.2.3,<0.3.0)
Requires-Dist: s2geometry (>=0.9.0,<0.10.0)
Requires-Dist: shapely (>=2.1,<3.0)
Requires-Dist: sqlalchemy (>=2.0.32,<3.0.0)
Requires-Dist: tqdm (>=4.67,<5.0)
Project-URL: Repository, https://github.com/manaakiwhenua/vector2dggs
